<?xml version="1.0" encoding="utf-8"?>
<data>
  <!-- 
	A <terrain> element represents what may be displayed by a component. It can be a collection of sprites overlayed and is uniquely 
	identified by an id property.  When the server communicates to the client about the map, it uses this id number to render various terrains.
  
		Attribute `id` 		=>  A unique identifer.
		Attribute `cost` 	=>	The cost related to pathing over this terrain object. A map tile selects the highest cost from all of it's terrain.
  
		Property `average`	=> The average color of this terrain, used for generating heatmaps for 1 tile to 1 pixel.
  
	Each terrain has a collection of <sprite> elements that are part of it's final render. 
		
		Attribute `order`		=>  The rendering order of this sprite.
		Attribute `underpile`	=>	If this terrain is rendered under the `treasure` sprite.
		
		Property `texture`	=> The path to the texture asset.
		Property `source`	=> The rectangular bounds used for the sprites from the texture.
		Property `offset`	=> The offset with which this sprite is rendered.
		
		Each sprite may have a collection of <frames>. Each <frame> is than a rectangular bounds and part of an animation.
		
			Attribute `step` => The ms delay between each frame.
			Attribute `keys` => The order of the frames as part of an animation.  You could loop an animation forward then in reverse, for example, with "0-5,5-0".
			
			
		How can I get a sprite to cycle colors, like fire, water, or whirlwind do? Each sprite can also have a <palette> element. It works similar to an animation.
		The animation will transform each color to the next over the specified `step` value. 
		
		<palette step="140" keys="0-7">
			<color source="(0,0,254,255)" />
			<color source="(0,0,243,255)" />
			<color source="(0,0,231,255)" />
			<color source="(0,0,219,255)" />
			<color source="(0,0,211,255)" />
			<color source="(0,0,199,255)" />
			<color source="(0,0,187,255)" />
			<color source="(0,0,179,255)" />
		</palette>
		
		Can I transform a color on a sprite to another? Yes! Such a transformation could allow you to change one palette cycle to another, for example water to fire 
		on a whirlwind.
			=> <color source="(0,0,179,255)" target="(0,0,0,255)" />
	
		A SPRITE CAN ONLY HAVE EITHER A FRAMES OR A PALETTE FOR ANIMATIONS. IT CAN NOT HAVE BOTH.
  -->



  <!-- 
	All artwork in the Tenser directory belongs to Tenser#2262 on Discord. Any use or modification outside of this project is prohibited.
	Please reach out to him if you wish to use the assets for your own purposes.
  -->
 
  <terrain id="622" cost="6">
    <sprite>
      <texture>Tenser\Terrain\Water-Wave-Horizontal</texture>
      <source>(0,0,1100,55)</source>
	  <offset>(45,45)</offset>
      <frames step="150" keys="0-19">
        <frame>(0,0,55,55)</frame>
        <frame>(55,0,55,55)</frame>
        <frame>(110,0,55,55)</frame>
        <frame>(165,0,55,55)</frame>
        <frame>(220,0,55,55)</frame>
        <frame>(275,0,55,55)</frame>
        <frame>(330,0,55,55)</frame>
        <frame>(385,0,55,55)</frame>
        <frame>(440,0,55,55)</frame>
        <frame>(495,0,55,55)</frame>
        <frame>(550,0,55,55)</frame>
        <frame>(605,0,55,55)</frame>
        <frame>(660,0,55,55)</frame>
        <frame>(715,0,55,55)</frame>
        <frame>(770,0,55,55)</frame>
        <frame>(825,0,55,55)</frame>
        <frame>(880,0,55,55)</frame>
        <frame>(935,0,55,55)</frame>
        <frame>(990,0,55,55)</frame>
        <frame>(1045,0,55,55)</frame>
      </frames>
    </sprite>
    <average>(11,82,214,255)</average>
  </terrain>

  <terrain id="623" cost="6">
    <sprite>
      <texture>Tenser\Terrain\Water-Wave-Vertical</texture>
      <source>(0,0,1100,55)</source>
	  <offset>(45,45)</offset>
      <frames step="150" keys="0-19">
        <frame>(0,0,55,55)</frame>
        <frame>(55,0,55,55)</frame>
        <frame>(110,0,55,55)</frame>
        <frame>(165,0,55,55)</frame>
        <frame>(220,0,55,55)</frame>
		<frame>(275,0,55,55)</frame>
        <frame>(330,0,55,55)</frame>
        <frame>(385,0,55,55)</frame>
        <frame>(440,0,55,55)</frame>
        <frame>(495,0,55,55)</frame>
        <frame>(550,0,55,55)</frame>
        <frame>(605,0,55,55)</frame>
        <frame>(660,0,55,55)</frame>
        <frame>(715,0,55,55)</frame>
        <frame>(770,0,55,55)</frame>
		<frame>(825,0,55,55)</frame>
        <frame>(880,0,55,55)</frame>
        <frame>(935,0,55,55)</frame>
        <frame>(990,0,55,55)</frame>
        <frame>(1045,0,55,55)</frame>
      </frames>
    </sprite>
    <average>(11,82,214,255)</average>
  </terrain>

  <terrain id="624">
    <sprite order="1" underpile="true">
      <texture>Tenser\Terrain\Trees</texture>
      <source>(0,0,100,100)</source>
    </sprite>
    <average>(52,105,23,255)</average>
  </terrain>
  <terrain id="625">
    <sprite order="1" underpile="true">
      <texture>Tenser\Terrain\Trees</texture>
      <source>(0,100,100,100)</source>
    </sprite>
    <average>(52,105,23,255)</average>
  </terrain>
  <terrain id="626">
    <sprite order="1" underpile="true">
      <texture>Tenser\Terrain\Trees</texture>
      <source>(100,100,100,100)</source>
    </sprite>
    <average>(52,105,23,255)</average>
  </terrain>
  <terrain id="627">
    <sprite order="1" underpile="true">
      <texture>Tenser\Terrain\Trees</texture>
      <source>(100,0,100,100)</source>
    </sprite>
    <average>(52,105,23,255)</average>
  </terrain>
  
  <terrain id="628"> <!-- Sewer Drain -->
    <sprite>
      <texture>Tenser\Terrain\Sewers</texture>
      <source>(0,0,100,100)</source>
    </sprite>
    <average>(136,120,186,255)</average>
  </terrain>
  <terrain id="629"> <!-- Sewer Floor -->
    <sprite>
      <texture>Tenser\Terrain\Sewers</texture>
      <source>(0,100,100,100)</source>
    </sprite>
    <average>(136,120,186,255)</average>
  </terrain>
  <terrain id="630"> <!-- Sewer Half-Wall (V) -->
    <sprite order="4">
      <texture>Tenser\Terrain\Sewers</texture>
      <source>(100,0,100,100)</source>
    </sprite>
    <average>(115,121,114,255)</average>
  </terrain>
  <terrain id="631"> <!-- Sewer Half-Wall (H) -->
    <sprite order="4">
      <texture>Tenser\Terrain\Sewers</texture>
      <source>(200,0,100,100)</source>
    </sprite>
    <average>(115,121,114,255)</average>
  </terrain>
  <terrain id="632"> <!-- Sewer Drain Round (V) -->
    <sprite order="7">
      <texture>Tenser\Terrain\Sewers</texture>
      <source>(100,100,100,100)</source>
    </sprite>
    <average>(169,88,101,255)</average>
  </terrain>
  <terrain id="633"> <!-- Sewer Drain Round (H) -->
    <sprite order="7">
      <texture>Tenser\Terrain\Sewers</texture>
      <source>(300,100,100,100)</source>
    </sprite>
    <average>(169,88,101,255)</average>
  </terrain> 
  <terrain id="634"> <!-- Sewer Drain Floor (H) -->
    <sprite order="7">
      <texture>Tenser\Terrain\Sewers</texture>
      <source>(300,0,100,100)</source>
    </sprite>
    <average>(169,88,101,255)</average>
  </terrain>
  <terrain id="635"> <!-- Sewer Drain Floor (V) -->
    <sprite order="7">
      <texture>Tenser\Terrain\Sewers</texture>
      <source>(200,100,100,100)</source>
    </sprite>
    <average>(169,88,101,255)</average>
  </terrain>
  <terrain id="636"> <!-- Sewer Wall Full (V) -->
    <sprite order="7">
      <texture>Tenser\Terrain\Sewers</texture>
      <source>(400,0,100,100)</source>
    </sprite>
    <average>(169,88,101,255)</average>
  </terrain>  
  <terrain id="637"> <!-- Sewer Wall Full (H) -->
    <sprite order="7">
      <texture>Tenser\Terrain\Sewers</texture>
      <source>(400,100,100,100)</source>
    </sprite>
    <average>(169,88,101,255)</average>
  </terrain>  
  <terrain id="638" cost="6"> <!-- Sewer Wall Ruins (H) -->
    <sprite order="3">
      <texture>Tenser\Terrain\Sewers</texture>
      <source>(0,200,100,100)</source>
    </sprite>
    <average>(169,88,101,255)</average>
  </terrain>    
  <terrain id="639" cost="6"> <!-- Sewer Wall Ruins (V) -->
    <sprite order="3">
      <texture>Tenser\Terrain\Sewers</texture>
      <source>(100,200,100,100)</source>
    </sprite>
    <average>(169,88,101,255)</average>
  </terrain>    
  
  
  <terrain id="640">
    <sprite order="4">
      <texture>Tenser/Terrain/BrokenPortalPillar</texture>
      <source>(0,0,100,100)</source>
    </sprite>
    <average>(174,174,174,255)</average>
  </terrain>
  <terrain id="641">
    <sprite order="4">
      <texture>Tenser/Terrain/BrokenStalagmite</texture>
      <source>(0,0,100,100)</source>
    </sprite>
    <average>(128,108,92,255)</average>
  </terrain>
  <terrain id="642">
    <sprite order="4">
      <texture>Tenser/Terrain/BrokenPortalPillar-2</texture>
      <source>(0,0,100,100)</source>
    </sprite>
    <average>(174,174,174,255)</average>
  </terrain>
  <terrain id="643">
    <sprite order="4">
      <texture>Tenser/Terrain/BrokenStalagmite-2</texture>
      <source>(0,0,100,100)</source>
    </sprite>
    <average>(128,108,92,255)</average>
  </terrain>
  
   <terrain id="650">  <!-- Vase (base) -->
    <sprite order="1">
      <texture>Tenser/Terrain/Pottery</texture>
      <source>(0,0,100,100)</source>
    </sprite>
  </terrain>
  <terrain id="651">  <!-- Vase (Single Ring) -->
    <sprite order="1">
      <texture>Tenser/Terrain/Pottery</texture>
      <source>(0,100,100,100)</source>
    </sprite>
  </terrain>
  <terrain id="652">  <!-- Vase (Double Ring) -->
    <sprite order="1">
      <texture>Tenser/Terrain/Pottery</texture>
      <source>(100,0,100,100)</source>
    </sprite>
  </terrain>
  <terrain id="653">  <!-- Vase (Pattern 1) -->
    <sprite order="1">
      <texture>Tenser/Terrain/Pottery</texture>
      <source>(200,0,100,100)</source>
    </sprite>
  </terrain>
  <terrain id="654">  <!-- Vase (Pattern 2) -->
    <sprite order="1">
      <texture>Tenser/Terrain/Pottery</texture>
      <source>(200,100,100,100)</source>
    </sprite>
  </terrain>
  <terrain id="655">  <!-- Vase (Pattern 3) -->
    <sprite order="1">
      <texture>Tenser/Terrain/Pottery</texture>
      <source>(200,200,100,100)</source>
    </sprite>
  </terrain>
  <terrain id="656">  <!-- Vase (Shadow) -->
    <sprite order="1">
      <texture>Tenser/Terrain/Pottery</texture>
      <source>(100,200,100,100)</source>
    </sprite>
  </terrain>
  
  <terrain id="658">  <!-- Vase (Broken) -->
    <sprite order="1">
      <texture>Tenser/Terrain/Pottery</texture>
      <source>(0,200,100,100)</source>
    </sprite>
  </terrain>
  <terrain id="659">  <!-- Vases -->
    <sprite order="1">
      <texture>Tenser/Terrain/Pottery</texture>
      <source>(100,100,100,100)</source>
    </sprite>
  </terrain>
</data>